airflow_fs/__init__.py
airflow_fs/operators.py
airflow_fs/testing.py
airflow_fs/hooks/__init__.py
airflow_fs/hooks/fs_hook.py
airflow_fs/hooks/ftp_hook.py
airflow_fs/hooks/hdfs_hook.py
airflow_fs/hooks/local_hook.py
airflow_fs/hooks/s3_hook.py
airflow_fs/hooks/sftp_hook.py
airflow_fs/ports/__init__.py
airflow_fs/ports/glob.py
airflow_fs-0.1.0.dist-info/AUTHORS.rst
airflow_fs-0.1.0.dist-info/LICENSE
airflow_fs-0.1.0.dist-info/METADATA
airflow_fs-0.1.0.dist-info/WHEEL
airflow_fs-0.1.0.dist-info/top_level.txt
airflow_fs-0.1.0.dist-info/RECORD
